{
    "responses": [
        "ржзржирзНржпржмрж╛ржж! рждрзБржорж┐ржУ ржЦрзБржм рж╕рзБржирзНржжрж░! ЁЯТЦ",
        "ржЖрж╣рж╛, ржХржд ржнрж╛рж▓рзЛ ржмрж▓рж▓рзЗ! ЁЯШК",
        "рждрзЛржорж╛рж░ ржХржерж╛ржпрж╝ ржЖржорж┐ ржЦрзБрж╢рж┐! тЬи",
        "ржЖржорж┐ рж▓ржЬрзНржЬрж╛ ржкрзЗржпрж╝рзЗ ржЧрзЗрж▓рж╛ржо! ЁЯШ│",
        "рждрзЛржорж╛рж░ ржкрзНрж░рж╢ржВрж╕рж╛ ржЖржорж╛рж░ ржЬржирзНржп ржЦрзБржм ржЧрзБрж░рзБрждрзНржмржкрзВрж░рзНржг! ЁЯМЯ",
        "ржзржирзНржпржмрж╛ржж ржкрзНрж░рж┐ржпрж╝! рждрзБржорж┐ ржЦрзБржм ржнрж╛рж▓рзЛ! ЁЯШШ",
        "ржУрж╣рзЛ! ржЖржорж╛рж░ ржорзБржЦ рж▓рж╛рж▓ рж╣ржпрж╝рзЗ ржЧрзЗржЫрзЗ! ЁЯНО",
        "рждрзЛржорж╛рж░ рж╕рж╛ржерзЗ ржХржерж╛ ржмрж▓рждрзЗ ржнрж╛рж▓рзЛ рж▓рж╛ржЧрзЗ! ЁЯТм",
        "рждрзБржорж┐ ржЦрзБржм ржорж┐рж╖рзНржЯрж┐! ЁЯНм",
        "ржЖржорж┐ ржЦрзБрж╢рж┐ ржпрзЗ рждрзЛржорж╛рж░ ржнрж╛рж▓рзЛ рж▓рж╛ржЧрж▓! ЁЯШД"
    ],
    "triggers": ["рж╕рзБржирзНржжрж░", "ржнрж╛рж▓рзЛ", "ржЪржорзОржХрж╛рж░", "ржЕрж╕рж╛ржзрж╛рж░ржг", "beautiful", "good", "nice", "awesome", "great", "ржорж┐рж╖рзНржЯрж┐"],
    "statistics": {
        "used_count": 0,
        "success_rate": 0,
        "last_used": null,
        "user_feedback": {}
    }
}